Metadata-Version: 1.1
Name: cmdb-supplement-syncpack
Version: 0.0.1
Summary: cmdb_supplement_syncpack
Home-page: UNKNOWN
Author: Sciencelogic, Inc.
Author-email: UNKNOWN
License: Sciencelogic, Inc.
Platform: UNKNOWN
Classifier: Development Status :: 3 - Alpha
Classifier: Intended Audience :: Developers
Classifier: Programming Language :: Python :: 3
